zendatastorage/ZenDataStorage.py
zendatastorage/__init__.py
zendatastorage-1.0.101.dist-info/METADATA
zendatastorage-1.0.101.dist-info/WHEEL
zendatastorage-1.0.101.dist-info/top_level.txt
zendatastorage-1.0.101.dist-info/RECORD
