Metadata-Version: 2.1
Name: zendatastorage
Version: 1.0.101
Summary: A Python package for processing data from .zenf files.
Home-page: UNKNOWN
Author: SpiralCreationsPyPi
Author-email: SpiralCreationsPyPi@proton.me
License: UNKNOWN
Keywords: Data Storage,Storage,Data
Platform: UNKNOWN
Classifier: Programming Language :: Python
Classifier: Operating System :: OS Independent
Requires-Dist: colorama
